netcalc/__init__.py
netcalc/cli.py
netcalc/command.py
netcalc/version.py
netcalc-0.6.2.dist-info/DESCRIPTION.rst
netcalc-0.6.2.dist-info/METADATA
netcalc-0.6.2.dist-info/RECORD
netcalc-0.6.2.dist-info/WHEEL
netcalc-0.6.2.dist-info/entry_points.txt
netcalc-0.6.2.dist-info/metadata.json
netcalc-0.6.2.dist-info/top_level.txt
