Metadata-Version: 2.0
Name: netcalc
Version: 0.6.2
Summary: Advanced network calculator and address planning helper
Home-page: https://github.com/israel-lugo/netcalc
Author: Israel G. Lugo
Author-email: israel.lugo@lugosys.com
License: GPLv3+
Platform: UNKNOWN
Classifier: Development Status :: 4 - Beta
Classifier: Intended Audience :: Education
Classifier: Intended Audience :: Information Technology
Classifier: Intended Audience :: Science/Research
Classifier: Intended Audience :: System Administrators
Classifier: Intended Audience :: Telecommunications Industry
Classifier: License :: OSI Approved :: GNU General Public License v3 or later (GPLv3+)
Classifier: Operating System :: Microsoft :: Windows
Classifier: Operating System :: OS Independent
Classifier: Operating System :: POSIX
Classifier: Operating System :: POSIX :: Linux
Classifier: Programming Language :: Python :: 2
Classifier: Programming Language :: Python :: 2.7
Classifier: Programming Language :: Python :: 3
Classifier: Programming Language :: Python :: 3.2
Classifier: Programming Language :: Python :: 3.3
Classifier: Programming Language :: Python :: 3.4
Classifier: Programming Language :: Python :: 3.5
Classifier: Topic :: Communications
Classifier: Topic :: Documentation
Classifier: Topic :: Education 
Classifier: Topic :: Internet
Classifier: Topic :: System :: Networking
Classifier: Topic :: System :: Networking :: Firewalls 
Classifier: Topic :: System :: Systems Administration
Classifier: Topic :: Utilities
Requires-Dist: netaddr (>=0.7.12)
